ImageProcessingApp/.env
ImageProcessingApp/__init__.py
ImageProcessingApp/cli.py
ImageProcessingApp/db.sqlite3
ImageProcessingApp/manage.py
ImageProcessingApp/App/__init__.py
ImageProcessingApp/App/admin.py
ImageProcessingApp/App/apply.py
ImageProcessingApp/App/applyUpdates.py
ImageProcessingApp/App/apps.py
ImageProcessingApp/App/imageProcessing.py
ImageProcessingApp/App/models.py
ImageProcessingApp/App/tests.py
ImageProcessingApp/App/urls.py
ImageProcessingApp/App/views.py
ImageProcessingApp/App/__pycache__/__init__.cpython-312.pyc
ImageProcessingApp/App/__pycache__/admin.cpython-312.pyc
ImageProcessingApp/App/__pycache__/apply.cpython-312.pyc
ImageProcessingApp/App/__pycache__/applyUpdates.cpython-312.pyc
ImageProcessingApp/App/__pycache__/apps.cpython-312.pyc
ImageProcessingApp/App/__pycache__/imageProcessing.cpython-312.pyc
ImageProcessingApp/App/__pycache__/models.cpython-312.pyc
ImageProcessingApp/App/__pycache__/urls.cpython-312.pyc
ImageProcessingApp/App/__pycache__/views.cpython-312.pyc
ImageProcessingApp/App/migrations/0001_initial.py
ImageProcessingApp/App/migrations/0002_category_operations_parameters.py
ImageProcessingApp/App/migrations/0003_rename_attributes_attribute_and_more.py
ImageProcessingApp/App/migrations/0004_parameter_default_value.py
ImageProcessingApp/App/migrations/0005_parameter_datatype.py
ImageProcessingApp/App/migrations/0006_rename_valuetype_parameter_inputtype.py
ImageProcessingApp/App/migrations/0007_option.py
ImageProcessingApp/App/migrations/0008_parameter_max_value_parameter_min_value.py
ImageProcessingApp/App/migrations/0009_alter_parameter_datatype_alter_parameter_inputtype.py
ImageProcessingApp/App/migrations/0010_alter_parameter_inputtype.py
ImageProcessingApp/App/migrations/0011_alter_parameter_max_value_alter_parameter_min_value.py
ImageProcessingApp/App/migrations/0012_rename_option_no_option_optionno_and_more.py
ImageProcessingApp/App/migrations/__init__.py
ImageProcessingApp_CPS-0.1.9.dist-info/METADATA
ImageProcessingApp_CPS-0.1.9.dist-info/WHEEL
ImageProcessingApp_CPS-0.1.9.dist-info/entry_points.txt
ImageProcessingApp_CPS-0.1.9.dist-info/top_level.txt
ImageProcessingApp_CPS-0.1.9.dist-info/RECORD
